EDFlib/__init__.py
EDFlib/edfreader.py
EDFlib/edfwriter.py
EDFlib_Python-1.0.8.dist-info/LICENSE
EDFlib_Python-1.0.8.dist-info/METADATA
EDFlib_Python-1.0.8.dist-info/WHEEL
EDFlib_Python-1.0.8.dist-info/top_level.txt
EDFlib_Python-1.0.8.dist-info/RECORD
