Metadata-Version: 2.1
Name: EDFlib-Python
Version: 1.0.8
Summary: Library to read/write EDF+/BDF+ files written in pure Python by the same author as the original EDFlib.
Home-page: https://www.teuniz.net/edflib_python/
Author: Teunis van Beelen
Author-email: teuniz@protonmail.com
License: UNKNOWN
Project-URL: Bug Tracker, https://gitlab.com/Teuniz/EDFlib-Python/-/issues
Platform: UNKNOWN
Classifier: Intended Audience :: Science/Research
Classifier: Programming Language :: Python :: 3
Classifier: License :: OSI Approved :: BSD License
Classifier: Operating System :: OS Independent
Requires-Python: >=3.5
License-File: LICENSE
Requires-Dist: numpy (>=1.17)
